{
  "20172": {
    "MATH CS ": {
      "courses": [
        {
          "capacity": "",
          "course_id": "",
          "course_title": "",
          "days": "",
          "enrollment": "",
          "instructor": "",
          "location": "",
          "sections": [],
          "status": "",
          "times": ""
        },
        {
          "capacity": "",
          "course_id": "",
          "course_title": "",
          "days": "",
          "enrollment": "",
          "instructor": "",
          "location": "",
          "sections": [],
          "status": "",
          "times": ""
        },
        {
          "capacity": "",
          "course_id": "",
          "course_title": "",
          "days": "",
          "enrollment": "",
          "instructor": "",
          "location": "",
          "sections": [],
          "status": "",
          "times": ""
        },
        {
          "capacity": "",
          "course_id": "",
          "course_title": "",
          "days": "",
          "enrollment": "",
          "instructor": "",
          "location": "",
          "sections": [],
          "status": "",
          "times": ""
        }
      ],
      "text": "Mathematics (Creative Studies) - MATH CS"
    },
    "text": "SPRING 2017"
  },
  "date": "2018-06-03T22:28:38.537229"
}